arxiv/vault/__init__.py
arxiv/vault/adapter.py
arxiv/vault/core.py
arxiv/vault/manager.py
arxiv/vault/middleware.py
arxiv/vault/hvac_extensions/__init__.py
arxiv/vault/hvac_extensions/v1.py
arxiv/vault/hvac_extensions/api/__init__.py
arxiv/vault/hvac_extensions/api/secrets_engines/__init__.py
arxiv/vault/hvac_extensions/api/secrets_engines/mysql.py
arxiv/vault/tests/__init__.py
arxiv/vault/tests/test_manager.py
arxiv/vault/tests/test_middleware.py
arxiv_vault-0.0.19.dist-info/DESCRIPTION.rst
arxiv_vault-0.0.19.dist-info/LICENSE.txt
arxiv_vault-0.0.19.dist-info/METADATA
arxiv_vault-0.0.19.dist-info/RECORD
arxiv_vault-0.0.19.dist-info/WHEEL
arxiv_vault-0.0.19.dist-info/metadata.json
arxiv_vault-0.0.19.dist-info/top_level.txt
