Metadata-Version: 2.0
Name: arxiv-vault
Version: 0.0.19
Summary: UNKNOWN
Home-page: UNKNOWN
Author: UNKNOWN
Author-email: UNKNOWN
License: UNKNOWN
Platform: UNKNOWN
Requires-Dist: dataclasses (>=0.6)
Requires-Dist: hvac (==0.8.2)
